recursive_action/__init__.py
recursive_action/recursive.py
recursive_action-0.1.1.dist-info/WHEEL
recursive_action-0.1.1.dist-info/METADATA
recursive_action-0.1.1.dist-info/RECORD
