Metadata-Version: 2.1
Name: recursive-action
Version: 0.1.1
Summary: Recursive classes and methods
Author: Dragon
Requires-Python: >=3.8,<4.0
Classifier: Programming Language :: Python :: 3
Classifier: Programming Language :: Python :: 3.10
Classifier: Programming Language :: Python :: 3.8
Classifier: Programming Language :: Python :: 3.9
